{
    "name": "Twilight Lake Dusk",
    "type": "dark",
    "semanticHighlighting": true,
    "colors": {
        "terminal.background": "#1e2229",
        "terminal.foreground": "#c0c5ce",
        "terminal.selectionBackground": "#265373",
        "terminal.selectionForeground": "#f1f2f4",
        "terminal.findMatchBackground": "#84587c3f",
        "terminalCursor.foreground": "#94cfdb",
        "terminalCursor.background": "#111318",
        "terminal.ansiBlack": "#111318",
        "terminal.ansiBrightBlack": "#1e2229",
        "terminal.ansiBlue": "#387aa8",
        "terminal.ansiBrightBlue": "#5e9dc9",
        "terminal.ansiCyan": "#3896a8",
        "terminal.ansiBrightCyan": "#5eb8c9",
        "terminal.ansiGreen": "#54924f",
        "terminal.ansiBrightGreen": "#79b474",
        "terminal.ansiMagenta": "#84587c",
        "terminal.ansiBrightMagenta": "#9f6f97",
        "terminal.ansiRed": "#82353c",
        "terminal.ansiBrightRed": "#a7444c",
        "terminal.ansiYellow": "#b89856",
        "terminal.ansiBrightYellow": "#d1b171",
        "terminal.ansiWhite": "#c0c5ce",
        "terminal.ansiBrightWhite": "#dddfe4",
        "minimap.foregroundOpacity": "#ffffff7f",
        "breadcrumb.background": "#111318",
        "editor.background": "#111318",
        "tab.activeBackground": "#111318",
        "minimap.background": "#1a1d233f",
        "editorGroup.border": "#1a1d23",
        "editorGroupHeader.tabsBackground": "#1a1d23",
        "sideBar.background": "#1a1d23",
        "sideBarSectionHeader.background": "#1a1d23",
        "sideBarTitle.background": "#1a1d23",
        "tab.inactiveBackground": "#1a1d23",
        "panel.background": "#1e2229",
        "panel.border": "#1e2229",
        "tab.hoverBackground": "#1e2229",
        "activityBar.background": "#272b35",
        "editorWidget.background": "#333a47",
        "sideBarSectionHeader.border": "#333a47",
        "scrollbarSlider.background": "#454d5f",
        "scrollbarSlider.hoverBackground": "#266673",
        "scrollbar.shadow": "#3896a83f",
        "editorGroup.dropBackground": "#3896a83f",
        "list.dropBackground": "#3896a83f",
        "sideBar.dropBackground": "#3896a83f",
        "tab.selectedBorderTop": "#3896a8",
        "scrollbarSlider.activeBackground": "#3896a8",
        "editorLineNumber.foreground": "#333a47",
        "disabledForeground": "#454d5f",
        "tab.inactiveForeground": "#454d5f",
        "activityBar.inactiveForeground": "#5e6a82",
        "editorLineNumber.activeForeground": "#5e6a82",
        "descriptionForeground": "#c0c5ce",
        "editor.foreground": "#c0c5ce",
        "foreground": "#c0c5ce",
        "icon.foreground": "#c0c5ce",
        "sideBar.foreground": "#c0c5ce",
        "sideBarTitle.foreground": "#c0c5ce",
        "sideBarSectionHeader.foreground": "#c0c5ce",
        "button.foreground": "#f6f7f8",
        "checkbox.foreground": "#f6f7f8",
        "dropdown.foreground": "#f6f7f8",
        "editorWidget.foreground": "#f6f7f8",
        "input.foreground": "#f6f7f8",
        "inputValidation.errorForeground": "#f6f7f8",
        "inputValidation.infoForeground": "#f6f7f8",
        "inputValidation.warningForeground": "#f6f7f8",
        "list.activeSelectionForeground": "#f6f7f8",
        "list.activeSelectionIconForeground": "#f6f7f8",
        "list.inactiveSelectionForeground": "#f6f7f8",
        "list.inactiveSelectionIconForeground": "#f6f7f8",
        "editorGutter.foldingControlForeground": "#5e9dc9",
        "textLink.foreground": "#3896a8",
        "tab.activeForeground": "#94cfdb",
        "errorForeground": "#a7444c",
        "editorWarning.foreground": "#a7444c",
        "editorError.foreground": "#a7444c",
        "checkbox.background": "#111318",
        "dropdown.background": "#111318",
        "input.background": "#111318",
        "inputOption.activeBorder": "#111318",
        "dropdown.listBackground": "#1e2229",
        "list.hoverBackground": "#272b35",
        "checkbox.border": "#333a47",
        "input.border": "#333a47",
        "dropdown.border": "#333a47",
        "input.placeholderForeground": "#454d5f",
        "inputOption.hoverBackground": "#454d5f",
        "listFilterWidget.background": "#454d5f",
        "toolbar.hoverBackground": "#454d5f",
        "button.background": "#265373",
        "list.filterMatchBackground": "#265373",
        "button.hoverBackground": "#387aa8",
        "inputOption.activeBackground": "#5e9dc9",
        "toolbar.activeBackground": "#5e9dc9",
        "inputValidation.warningBorder": "#9b5741",
        "inputValidation.warningBackground": "#9b5741",
        "list.warningForeground": "#9b5741",
        "inputValidation.errorBorder": "#82353c",
        "inputValidation.errorBackground": "#82353c",
        "list.errorForeground": "#82353c",
        "activityBarBadge.foreground": "#111318",
        "activityErrorBadge.foreground": "#111318",
        "activityWarningBadge.foreground": "#111318",
        "badge.foreground": "#111318",
        "minimap.selectionHighlight": "#265373bf",
        "list.activeSelectionBackground": "#265373",
        "list.inactiveSelectionBackground": "#265373",
        "minimap.findMatchHighlight": "#387aa8bf",
        "selection.background": "#387aa8",
        "tree.indentGuidesStroke": "#266673",
        "tree.inactiveIndentGuidesStroke": "#266673",
        "activityBar.activeBorder": "#3896a8",
        "activityBar.foreground": "#3896a8",
        "editorGutter.addedBackground": "#396336",
        "minimapGutter.addedBackground": "#396336",
        "minimap.warningHighlight": "#be6c50bf",
        "activityWarningBadge.background": "#d08870",
        "minimap.errorHighlight": "#82353cbf",
        "activityErrorBadge.background": "#bf6169",
        "editorGutter.deletedBackground": "#bf6169",
        "minimapGutter.deletedBackground": "#bf6169",
        "minimapGutter.modifiedBackground": "#d1b171bf",
        "activityBarBadge.background": "#5eb8c9",
        "badge.background": "#5eb8c9",
        "sash.hoverBorder": "#5eb8c9",
        "tab.dragAndDropBorder": "#5eb8c9",
        "focusBorder": "#5eb8c9",
        "progressBar.background": "#5eb8c9",
        "editorGutter.modifiedBackground": "#d1b171",
        "editorMinimap.inlineChatInserted": "#d1b171"
    },
    "semanticTokenColors": {
        "class.typeHint": "#3896a8",
        "enum.typeHint": "#3896a8",
        "module": {
            "foreground": "#3896a8",
            "fontStyle": "underline"
        },
        "class.declaration": {
            "foreground": "#5eb8c9",
            "fontStyle": "bold"
        },
        "function.declaration": {
            "foreground": "#5eb8c9",
            "fontStyle": "bold"
        },
        "method.declaration": {
            "foreground": "#5eb8c9",
            "fontStyle": "bold"
        },
        "class": "#5eb8c9",
        "enum": "#5eb8c9",
        "function": "#5eb8c9",
        "method": "#5eb8c9",
        "function.decorator": "#5eb8c9",
        "property": "#9f6f97",
        "property.declaration": "#9f6f97",
        "enumMember": "#9f6f97",
        "selfParameter": {
            "foreground": "#9f6f97",
            "fontStyle": "bold"
        },
        "clsParameter": {
            "foreground": "#9f6f97",
            "fontStyle": "bold"
        }
    },
    "tokenColors": [
        {
            "scope": "comment",
            "settings": {
                "foreground": "#454d5f",
                "fontStyle": "italic"
            }
        },
        {
            "scope": "punctuation.definition.comment",
            "settings": {
                "foreground": "#454d5f",
                "fontStyle": "italic"
            }
        },
        {
            "scope": [
                "punctuation.parenthesis",
                "punctuation.definition.arguments",
                "punctuation.separator",
                "punctuation.section.class.begin",
                "punctuation.section.function.begin"
            ],
            "settings": {
                "foreground": "#5e6a82"
            }
        },
        {
            "scope": [
                "meta.function-call.arguments keyword.operator.assignment"
            ],
            "settings": {
                "foreground": "#5e6a82"
            }
        },
        {
            "scope": [
                "constant.character.format.placeholder",
                "storage.type.string",
                "punctuation.definition.string,"
            ],
            "settings": {
                "foreground": "#396336",
                "fontStyle": "italic"
            }
        },
        {
            "scope": "string",
            "settings": {
                "foreground": "#54924f",
                "fontStyle": "italic"
            }
        },
        {
            "scope": [
                "constant.language",
                "constant.numeric"
            ],
            "settings": {
                "foreground": "#79b474"
            }
        },
        {
            "scope": "variable.parameter.function-call",
            "settings": {
                "foreground": "#387aa8"
            }
        },
        {
            "scope": [
                "keyword.other.DML.sql",
                "keyword.other.DDL",
                "keyword.other.alias.sql",
                "keyword.other.sql"
            ],
            "settings": {
                "foreground": "#387aa8"
            }
        },
        {
            "scope": [
                "storage.type.class",
                "storage.type.function",
                "storage.modifier"
            ],
            "settings": {
                "foreground": "#387aa8",
                "fontStyle": "bold"
            }
        },
        {
            "scope": [
                "keyword.control.flow",
                "keyword.control.import",
                "keyword.operator.logical"
            ],
            "settings": {
                "foreground": "#387aa8",
                "fontStyle": "bold"
            }
        },
        {
            "scope": [
                "keyword.operator.arithmetic",
                "keyword.operator.assignment"
            ],
            "settings": {
                "foreground": "#387aa8"
            }
        },
        {
            "scope": [
                "support.type.property-name.json",
                "entity.name.tag.yaml"
            ],
            "settings": {
                "foreground": "#5e9dc9"
            }
        },
        {
            "scope": "punctuation.definition.decorator",
            "settings": {
                "foreground": "#266673"
            }
        },
        {
            "scope": "meta.function-call.generic.python",
            "settings": {
                "foreground": "#5eb8c9"
            }
        },
        {
            "scope": "support.function.string.sql",
            "settings": {
                "foreground": "#5eb8c9"
            }
        },
        {
            "scope": "support.variable.magic",
            "settings": {
                "foreground": "#bf6169"
            }
        },
        {
            "scope": "constant.other.caps",
            "settings": {
                "foreground": "#bf6169"
            }
        },
        {
            "scope": "constant.other.table-name.sql",
            "settings": {
                "foreground": "#9f6f97"
            }
        }
    ]
}